metricax/__init__.py
metricax/py.typed
metricax/bayesian/__init__.py
metricax/bayesian/bayes_theorem.py
metricax/bayesian/beta_distributions.py
metricax/bayesian/conjugate_priors.py
metricax/bayesian/utils.py
metricax/bayesian/examples/__init__.py
metricax/bayesian/examples/ab_testing.py
metricax/bayesian/examples/data_updates.py
metricax/bayesian/examples/spam_filter.py
metricax/bayesian/tests/__init__.py
metricax/bayesian/tests/test_bayes_theorem.py
metricax/bayesian/tests/test_beta_distributions.py
metricax/bayesian/tests/test_utils.py
metricax/info_theory/__init__.py
metricax/info_theory/coding_theory.py
metricax/info_theory/distance_measures.py
metricax/info_theory/entropy.py
metricax/info_theory/mutual_info.py
metricax/info_theory/utils.py
metricax/info_theory/examples/__init__.py
metricax/info_theory/examples/coding_example.py
metricax/info_theory/examples/entropy_example.py
metricax/info_theory/examples/mutual_info_example.py
metricax/info_theory/tests/__init__.py
metricax/info_theory/tests/test_coding_theory.py
metricax/info_theory/tests/test_distance_measures.py
metricax/info_theory/tests/test_entropy.py
metricax/info_theory/tests/test_mutual_info.py
metricax/info_theory/tests/test_utils.py
metricax-0.2.1.dist-info/licenses/LICENSE
metricax-0.2.1.dist-info/METADATA
metricax-0.2.1.dist-info/WHEEL
metricax-0.2.1.dist-info/top_level.txt
metricax-0.2.1.dist-info/RECORD
