Metadata-Version: 2.4
Name: metricax
Version: 0.2.1
Summary: Professional mathematical and statistical toolkit for Python - Bayesian statistics, information theory, and numerical computing
Author-email: MD Shoaib Uddin Chanda <mdshoaibuddinchanda@gmail.com>
Maintainer-email: MD Shoaib Uddin Chanda <mdshoaibuddinchanda@gmail.com>
License: MIT
Project-URL: Homepage, https://github.com/metricax/metricax
Project-URL: Documentation, https://metricax.readthedocs.io
Project-URL: Repository, https://github.com/metricax/metricax.git
Project-URL: Bug Tracker, https://github.com/metricax/metricax/issues
Project-URL: Changelog, https://github.com/metricax/metricax/blob/main/CHANGELOG.md
Project-URL: Discussions, https://github.com/metricax/metricax/discussions
Keywords: mathematics,statistics,bayesian,information-theory,entropy,machine-learning,data-science,probability,numerical-computing,scientific-computing
Classifier: Development Status :: 4 - Beta
Classifier: Intended Audience :: Developers
Classifier: Intended Audience :: Science/Research
Classifier: Intended Audience :: Education
Classifier: License :: OSI Approved :: MIT License
Classifier: Operating System :: OS Independent
Classifier: Programming Language :: Python :: 3
Classifier: Programming Language :: Python :: 3.8
Classifier: Programming Language :: Python :: 3.9
Classifier: Programming Language :: Python :: 3.10
Classifier: Programming Language :: Python :: 3.11
Classifier: Programming Language :: Python :: 3.12
Classifier: Topic :: Scientific/Engineering
Classifier: Topic :: Scientific/Engineering :: Mathematics
Classifier: Topic :: Scientific/Engineering :: Information Analysis
Classifier: Topic :: Software Development :: Libraries :: Python Modules
Classifier: Typing :: Typed
Requires-Python: >=3.8
License-File: LICENSE
Provides-Extra: dev
Requires-Dist: pytest>=7.0.0; extra == "dev"
Requires-Dist: pytest-cov>=4.0.0; extra == "dev"
Requires-Dist: pytest-benchmark>=4.0.0; extra == "dev"
Requires-Dist: black>=22.0.0; extra == "dev"
Requires-Dist: flake8>=5.0.0; extra == "dev"
Requires-Dist: mypy>=1.0.0; extra == "dev"
Requires-Dist: isort>=5.0.0; extra == "dev"
Requires-Dist: bandit>=1.7.0; extra == "dev"
Requires-Dist: safety>=2.0.0; extra == "dev"
Provides-Extra: examples
Requires-Dist: jupyter>=1.0.0; extra == "examples"
Requires-Dist: matplotlib>=3.5.0; extra == "examples"
Requires-Dist: seaborn>=0.11.0; extra == "examples"
Requires-Dist: pandas>=1.3.0; extra == "examples"
Requires-Dist: numpy>=1.21.0; extra == "examples"
Provides-Extra: docs
Requires-Dist: sphinx>=5.0.0; extra == "docs"
Requires-Dist: sphinx-rtd-theme>=1.0.0; extra == "docs"
Requires-Dist: myst-parser>=0.18.0; extra == "docs"
Provides-Extra: all
Requires-Dist: metricax[dev,docs,examples]; extra == "all"
Dynamic: license-file
